README.md
setup.py
tap_liveperson/__init__.py
tap_liveperson/client.py
tap_liveperson/config.py
tap_liveperson/state.py
tap_liveperson/unzip.py
tap_liveperson.egg-info/PKG-INFO
tap_liveperson.egg-info/SOURCES.txt
tap_liveperson.egg-info/dependency_links.txt
tap_liveperson.egg-info/entry_points.txt
tap_liveperson.egg-info/requires.txt
tap_liveperson.egg-info/top_level.txt
tap_liveperson/schemas/agent_activity.json
tap_liveperson/schemas/agent_groups.json
tap_liveperson/schemas/agent_state_distribution.json
tap_liveperson/schemas/agent_status.json
tap_liveperson/schemas/engagement_history.json
tap_liveperson/schemas/messaging_interactions.json
tap_liveperson/schemas/messaging_queue_health.json
tap_liveperson/schemas/queue_health.json
tap_liveperson/schemas/skills.json
tap_liveperson/schemas/users.json
tap_liveperson/streams/__init__.py
tap_liveperson/streams/agent_activity.py
tap_liveperson/streams/agent_groups.py
tap_liveperson/streams/agent_state_distribution.py
tap_liveperson/streams/agent_status.py
tap_liveperson/streams/base.py
tap_liveperson/streams/engagement_history.py
tap_liveperson/streams/messaging_interactions.py
tap_liveperson/streams/messaging_queue_health.py
tap_liveperson/streams/queue_health.py
tap_liveperson/streams/skills.py
tap_liveperson/streams/users.py