Metadata-Version: 1.1
Name: tap-liveperson
Version: 1.0.0
Summary: Singer.io tap for extracting data from the LivePerson API
Home-page: http://fishtownanalytics.com
Author: Fishtown Analytics
Author-email: UNKNOWN
License: UNKNOWN
Platform: UNKNOWN
Classifier: Programming Language :: Python :: 3 :: Only
